newscatcherapi/__init__.py
newscatcherapi/const.py
newscatcherapi/newscatcherapi_auth.py
newscatcherapi/newscatcherapi_client.py
newscatcherapi/newscatcherapi_exception.py
newscatcherapi/utils.py
newscatcherapi-0.7.3.dist-info/LICENSE
newscatcherapi-0.7.3.dist-info/METADATA
newscatcherapi-0.7.3.dist-info/WHEEL
newscatcherapi-0.7.3.dist-info/RECORD
