Metadata-Version: 2.1
Name: newscatcherapi
Version: 0.7.3
Summary: NewsCatcher News API V2 SDK for Python
Home-page: https://newscatcherapi.com/
License: MIT
Keywords: News,RSS,Scraping,Data Mining,News Extraction
Author: Maksym Sugonyaka
Author-email: maksym@newscatcherapi.com
Requires-Python: >=3.6.0
Classifier: License :: OSI Approved :: MIT License
Classifier: Programming Language :: Python :: 3
Classifier: Programming Language :: Python :: 3.6
Classifier: Programming Language :: Python :: 3.7
Classifier: Programming Language :: Python :: 3.8
Classifier: Programming Language :: Python :: 3.9
Classifier: Programming Language :: Python :: 3.10
Classifier: Programming Language :: Python :: 3.11
Classifier: Programming Language :: Python :: 3.12
Requires-Dist: dateparser (>=0.7.6)
Requires-Dist: requests (>=2.24.0)
